{
  "\"initiatiefnota Ploumen AND Van Gerven AND Ellemeet AND Big Farma\"": [
    {
      "identifier": [
        "kst-34834-16"
      ],
      "title": [
        "Initiatiefnota van de leden Ploumen, Van Gerven en Ellemeet: “Big Farma: niet gezond!”; Verslag van een notaoverleg; Verslag van een notaoverleg, gehouden op 10 december 2018, over de initiatiefnota van de leden Ploumen, Van Gerven en Ellemeet: “Big Farma: niet gezond!”"
      ]
    },
    {
      "identifier": [
        "kst-34834-7"
      ],
      "title": [
        "Initiatiefnota van de leden Dijksma, Van Gerven en Ellemeet: “Big Farma: niet gezond!”; Brief lid / fractie; Brief van het lid Ploumen inzake overname van de verdediging van de initiatiefnota"
      ]
    },
    {
      "identifier": [
        "kst-29477-607"
      ],
      "title": [
        "Geneesmiddelenbeleid; Verslag van een algemeen overleg; Verslag van een algemeen overleg, gehouden op 6 juni 2019, over Geneesmiddelenbeleid"
      ]
    },
    {
      "identifier": [
        "kst-34834-10"
      ],
      "title": [
        "Initiatiefnota van de leden Ploumen, Van Gerven en Ellemeet: “Big Farma: niet gezond!”; Motie; Motie van het lid Van den Berg over het stroomlijnen van publieke geldstromen voor geneesmiddelenontwikkeling"
      ]
    },
    {
      "identifier": [
        "kst-34834-12"
      ],
      "title": [
        "Initiatiefnota van de leden Ploumen, Van Gerven en Ellemeet: “Big Farma: niet gezond!”; Motie; Motie van het lid Hijink c.s. over het indammen van verkoop en marketing via artsenbezoekers"
      ]
    },
    {
      "identifier": [
        "kst-34834-13"
      ],
      "title": [
        "Initiatiefnota van de leden Ploumen, Van Gerven en Ellemeet: “Big Farma: niet gezond!”; Motie; Motie van het lid Kerstens c.s. over onderzoek naar de omvang van voorraden geneesmiddelen"
      ]
    },
    {
      "identifier": [
        "kst-34834-14"
      ],
      "title": [
        "Initiatiefnota van de leden Ploumen, Van Gerven en Ellemeet: “Big Farma: niet gezond!”; Motie; Motie van het lid Kerstens c.s. over de invoering van licentieovereenkomsten"
      ]
    },
    {
      "identifier": [
        "kst-34834-8"
      ],
      "title": [
        "Initiatiefnota van de leden Ploumen, Van Gerven en Ellemeet: “Big Farma: niet gezond!”; Motie; Motie van het lid Westerveld c.s. over het ondersteunen van de inzet van magistrale bereiding"
      ]
    },
    {
      "identifier": [
        "kst-34834-9"
      ],
      "title": [
        "Initiatiefnota van de leden Ploumen, Van Gerven en Ellemeet: “Big Farma: niet gezond!”; Motie; Motie van het lid Van den Berg over onderzoek naar biomarkers"
      ]
    },
    {
      "identifier": [
        "kst-34834-17"
      ],
      "title": [
        "Initiatiefnota van de leden Ploumen, Van Gerven en Ellemeet: “Big Farma: niet gezond!”; Motie (gewijzigd/nader); Gewijzigde motie van het lid Van den Berg over geneesmiddelen voorzien van een biomarker (t.v.v. 34834-9)"
      ]
    },
    {
      "identifier": [
        "kst-34834-15"
      ],
      "title": [
        "Initiatiefnota van de leden Ploumen, Van Gerven en Ellemeet: “Big Farma: niet gezond!”; Motie; Motie van het lid Kerstens c.s. over een Noors model met tien referentielanden"
      ]
    },
    {
      "identifier": [
        "kst-34834-11"
      ],
      "title": [
        "Initiatiefnota van de leden Ploumen, Van Gerven en Ellemeet: “Big Farma: niet gezond!”; Motie; Motie van het lid Hijink c.s. over een onafhankelijk onderzoeksfonds geneesmiddelen"
      ]
    },
    {
      "identifier": [
        "kst-29477-557"
      ],
      "title": [
        "Geneesmiddelenbeleid; Verslag van een algemeen overleg; Verslag van een algemeen overleg, gehouden op 7 februari 2019, over geneesmiddelenbeleid"
      ]
    },
    {
      "identifier": [
        "kst-21501-31-506"
      ],
      "title": [
        "Raad voor de Werkgelegenheid, Sociaal Beleid, Volksgezondheid en Consumentenzaken; Verslag van een algemeen overleg; Verslag van een algemeen overleg, gehouden op 5 december 2018, over de EU-Gezondheidsraad d.d. 7 december 2018"
      ]
    }
  ],
  "\"motie AND Van den Berg AND biomarkers\"": [
    {
      "identifier": [
        "kst-34834-16"
      ],
      "title": [
        "Initiatiefnota van de leden Ploumen, Van Gerven en Ellemeet: “Big Farma: niet gezond!”; Verslag van een notaoverleg; Verslag van een notaoverleg, gehouden op 10 december 2018, over de initiatiefnota van de leden Ploumen, Van Gerven en Ellemeet: “Big Farma: niet gezond!”"
      ]
    },
    {
      "identifier": [
        "kst-34834-9"
      ],
      "title": [
        "Initiatiefnota van de leden Ploumen, Van Gerven en Ellemeet: “Big Farma: niet gezond!”; Motie; Motie van het lid Van den Berg over onderzoek naar biomarkers"
      ]
    },
    {
      "identifier": [
        "kst-29477-557"
      ],
      "title": [
        "Geneesmiddelenbeleid; Verslag van een algemeen overleg; Verslag van een algemeen overleg, gehouden op 7 februari 2019, over geneesmiddelenbeleid"
      ]
    },
    {
      "identifier": [
        "kst-29477-607"
      ],
      "title": [
        "Geneesmiddelenbeleid; Verslag van een algemeen overleg; Verslag van een algemeen overleg, gehouden op 6 juni 2019, over Geneesmiddelenbeleid"
      ]
    },
    {
      "identifier": [
        "kst-34834-17"
      ],
      "title": [
        "Initiatiefnota van de leden Ploumen, Van Gerven en Ellemeet: “Big Farma: niet gezond!”; Motie (gewijzigd/nader); Gewijzigde motie van het lid Van den Berg over geneesmiddelen voorzien van een biomarker (t.v.v. 34834-9)"
      ]
    },
    {
      "identifier": [
        "kst-29477-532"
      ],
      "title": [
        "Geneesmiddelenbeleid; Brief regering; Voortgangsbrief geneesmiddelenbeleid"
      ]
    },
    {
      "identifier": [
        "kst-29477-602"
      ],
      "title": [
        "Geneesmiddelenbeleid; Brief regering; Uitbreiding Integraal pakket aan maatregelen en Overhevelingen"
      ]
    },
    {
      "identifier": [
        "blg-896893"
      ],
      "title": [
        "Gezondheidseffecten van blootstelling aan stroomstootwapens (Tasers) in de context van wetshandhaving"
      ]
    }
  ],
  "\"gewijzigde motie-Van den Berg AND dossiernummer\"": []
}